{
  "type": "game",
  "title": "Olá. Como está?",
  "subtitle": "Assista a este vídeo incrível!",
  "videoUrl": "https://www.youtube.com/embed/jfKfPfyJRdk",
  "formFields": {
    "numberOfFields": 4,
    "fields": [
      {
        "fieldType": "email",
        "fieldTitle": "Email"
      },
      {
        "fieldType": "text",
        "fieldTitle": "Nome"
      },
      {
        "fieldType": "text",
        "fieldTitle": "Telefone Celular"
      },
      {
        "fieldType": "text",
        "fieldTitle": "Gênero"
      }
    ]
  },
  "consentCheckbox": {
    "visible": true,
    "text": "Quero participar"
  }
}
